scribe_search/__init__.py
scribe_search/cli.py
scribe_search/data.py
scribe_search/exceptions.py
scribe_search/logger.py
scribe_search/main.py
scribe_search/search.py
scribe_search/utils.py
scribe_search/loaders/__init__.py
scribe_search/loaders/auto.py
scribe_search/loaders/srt.py
scribe_search/loaders/video.py
scribe_search/loaders/youtube.py
scribe_search-0.1.0.dist-info/METADATA
scribe_search-0.1.0.dist-info/WHEEL
scribe_search-0.1.0.dist-info/entry_points.txt
scribe_search-0.1.0.dist-info/top_level.txt
scribe_search-0.1.0.dist-info/RECORD
